LICENSE
blendernc/UI_operators.py
blendernc/__init__.py
blendernc/addon_updater.py
blendernc/addon_updater_ops.py
blendernc/blendernc.py
blendernc/core/__init__.py
blendernc/core/dates.py
blendernc/core/lic/ReadMe.md
blendernc/core/lic/__init__.py
blendernc/core/lic/lic_internal.pyx
blendernc/core/logging.py
blendernc/core/sys_utils.py
blendernc/core/update_ui.py
blendernc/decorators.py
blendernc/get_utils.py
blendernc/handlers.py
blendernc/image.py
blendernc/messages.py
blendernc/nodes/BlenderNC_NT_node_template.py
blendernc/nodes/__init__.py
blendernc/nodes/cmaps/__init__.py
blendernc/nodes/cmaps/cmapsnode.py
blendernc/nodes/cmaps/utils_colorramp.py
blendernc/nodes/grid/BlenderNC_NT_input_grid.py
blendernc/nodes/grid/BlenderNC_NT_resolution.py
blendernc/nodes/grid/BlenderNC_NT_rotate_lon.py
blendernc/nodes/grid/__init__.py
blendernc/nodes/inputs/BlenderNC_NT_datacube.py
blendernc/nodes/inputs/BlenderNC_NT_path.py
blendernc/nodes/inputs/BlenderNC_NT_range.py
blendernc/nodes/inputs/BlenderNC_NT_tutorial.py
blendernc/nodes/inputs/__init__.py
blendernc/nodes/math/BlenderNC_NT_derivatives.py
blendernc/nodes/math/BlenderNC_NT_math.py
blendernc/nodes/math/BlenderNC_NT_transpose.py
blendernc/nodes/math/__init__.py
blendernc/nodes/node_categories.py
blendernc/nodes/node_tree.py
blendernc/nodes/outputs/BlenderNC_NT_output.py
blendernc/nodes/outputs/BlenderNC_NT_preloader.py
blendernc/nodes/outputs/__init__.py
blendernc/nodes/outputs/particle_advection.py
blendernc/nodes/selecting/BlenderNC_NT_drop_dims.py
blendernc/nodes/selecting/BlenderNC_NT_select_axis.py
blendernc/nodes/selecting/BlenderNC_NT_select_time.py
blendernc/nodes/selecting/BlenderNC_NT_sort.py
blendernc/nodes/selecting/__init__.py
blendernc/nodes/shortcuts/BlenderNC_NT_basic_nodes.py
blendernc/nodes/shortcuts/__init__.py
blendernc/operators.py
blendernc/panels.py
blendernc/preferences.py
blendernc/python_functions.py
blendernc/sockets.py
blendernc/translations.py
blendernc/workspace/startup.blend
blendernc-0.6.0.dist-info/LICENSE
blendernc-0.6.0.dist-info/WHEEL
blendernc-0.6.0.dist-info/METADATA
blendernc-0.6.0.dist-info/RECORD
