Metadata-Version: 2.1
Name: blendernc
Version: 0.6.0
Summary: Blender add-on to import datasets (netCDF, grib, and zarr)
Home-page: https://github.com/blendernc/blendernc
License: MIT
Keywords: visualization,3D
Author: josuemtzmo
Author-email: josue.martinezmoreno@anu.edu.au
Requires-Python: >=3.7,<3.10
Classifier: Development Status :: 3 - Alpha
Classifier: Environment :: Plugins
Classifier: Intended Audience :: Science/Research
Classifier: License :: OSI Approved :: MIT License
Classifier: Operating System :: OS Independent
Classifier: Programming Language :: Python :: 3
Classifier: Programming Language :: Python :: 3.7
Classifier: Programming Language :: Python :: 3.8
Classifier: Programming Language :: Python :: 3.9
Classifier: Topic :: Scientific/Engineering :: GIS
Classifier: Topic :: Scientific/Engineering :: Physics
Classifier: Topic :: Scientific/Engineering :: Visualization
Classifier: Topic :: Software Development :: Libraries :: Python Modules
Requires-Dist: Bottleneck (==1.2.1)
Requires-Dist: cfgrib (>=0.9.9,<0.10.0)
Requires-Dist: click (>=7,<8)
Requires-Dist: cmocean (>=2.0,<3.0)
Requires-Dist: colorcet (>=3.0.0,<4.0.0)
Requires-Dist: dask (>=2021.8.1,<2022.0.0)
Requires-Dist: ecmwflibs (>=0.4.5,<0.5.0)
Requires-Dist: matplotlib (>=3.4.3,<4.0.0)
Requires-Dist: netCDF4 (>=1.5.7,<2.0.0)
Requires-Dist: numpy (>=1.21.2,<2.0.0)
Requires-Dist: pooch (>=1.5.1,<2.0.0)
Requires-Dist: psutil (>=5.8.0,<6.0.0)
Requires-Dist: scipy (>=1.7.1,<2.0.0)
Requires-Dist: toml (>=0.10.2,<0.11.0)
Requires-Dist: toolz (>=0.11.1,<0.12.0)
Requires-Dist: xarray (>=0.19.0,<0.20.0)
Requires-Dist: zarr (>=2.9.4,<3.0.0)
Project-URL: Changelog, https://github.com/blendernc/blendernc/blob/master/CHANGELOG.md
Project-URL: Repository, https://github.com/blendernc/blendernc
